zosnel/__init__.py
zosnel/all_func.py
zosnel/main.py
zosnel-0.0.3.dist-info/LICENSE
zosnel-0.0.3.dist-info/METADATA
zosnel-0.0.3.dist-info/WHEEL
zosnel-0.0.3.dist-info/top_level.txt
zosnel-0.0.3.dist-info/RECORD
