Metadata-Version: 2.1
Name: zosnel
Version: 0.0.3
Summary: A python framework for simple web apps.
Home-page: https://github.com/Zosnel/Zosnel
Author: SachchitMishra
Author-email: sachchitroymishra@hotmail.com
Classifier: Programming Language :: Python :: 3
Classifier: License :: OSI Approved :: MIT License
Classifier: Operating System :: OS Independent
Requires-Python: >=3.6
License-File: LICENSE
